setup.py
django_agpl/__init__.py
django_agpl/app_settings.py
django_agpl/http.py
django_agpl/signals.py
django_agpl/urls.py
django_agpl/utils.py
django_agpl/views.py
django_agpl.egg-info/PKG-INFO
django_agpl.egg-info/SOURCES.txt
django_agpl.egg-info/dependency_links.txt
django_agpl.egg-info/requires.txt
django_agpl.egg-info/top_level.txt
django_agpl/templates/includes/agpl-3.0.html
django_agpl/templates/includes/agpl-3.0.txt