Metadata-Version: 1.0
Name: django-agpl
Version: 4.0.0
Summary: Django application to assist GNU AGPL compliance
Home-page: https://chris-lamb.co.uk/projects/django-agpl
Author: Chris Lamb
Author-email: chris@chris-lamb.co.uk
License: UNKNOWN
Platform: UNKNOWN
